{
  "gitSyncId": "68c175fe5467961c770340fb_48503559-118a-4eda-a615-fd49ef2e0591",
  "id": "Product View_UpdateQuery",
  "pluginId": "mysql-plugin",
  "pluginType": "DB",
  "unpublishedAction": {
    "actionConfiguration": {
      "body": "UPDATE WrARJWM7_actionscheduler_actions SET\n\t\thook = '{{update_form.fieldState.hook.isVisible ? update_form.formData.hook : update_form.sourceData.hook}}',\n\t\tstatus = '{{update_form.fieldState.status.isVisible ? update_form.formData.status : update_form.sourceData.status}}',\n    scheduled_date_gmt = '{{update_form.fieldState.scheduled_date_gmt.isVisible ? update_form.formData.scheduled_date_gmt : update_form.sourceData.scheduled_date_gmt}}',\n\t\tscheduled_date_local = '{{update_form.fieldState.scheduled_date_local.isVisible ? update_form.formData.scheduled_date_local : update_form.sourceData.scheduled_date_local}}',\n\t\tpriority = '{{update_form.fieldState.priority.isVisible ? update_form.formData.priority : update_form.sourceData.priority}}',\n\t\targs = '{{update_form.fieldState.args.isVisible ? update_form.formData.args : update_form.sourceData.args}}',\n\t\tschedule = '{{update_form.fieldState.schedule.isVisible ? update_form.formData.schedule : update_form.sourceData.schedule}}',\n\t\tgroup_id = '{{update_form.fieldState.group_id.isVisible ? update_form.formData.group_id : update_form.sourceData.group_id}}',\n\t\tattempts = '{{update_form.fieldState.attempts.isVisible ? update_form.formData.attempts : update_form.sourceData.attempts}}',\n\t\tlast_attempt_gmt = '{{update_form.fieldState.last_attempt_gmt.isVisible ? update_form.formData.last_attempt_gmt : update_form.sourceData.last_attempt_gmt}}',\n\t\tlast_attempt_local = '{{update_form.fieldState.last_attempt_local.isVisible ? update_form.formData.last_attempt_local : update_form.sourceData.last_attempt_local}}'\n  WHERE action_id = {{data_table.selectedRow.action_id}};",
      "encodeParamsToggle": true,
      "paginationType": "NONE",
      "pluginSpecifiedTemplates": [
        {
          "value": true
        }
      ],
      "timeoutInMillisecond": 10000
    },
    "confirmBeforeExecute": false,
    "datasource": {
      "id": "Untitled datasource 1",
      "isAutoGenerated": false,
      "name": "Untitled datasource 1",
      "pluginId": "mysql-plugin"
    },
    "dynamicBindingPathList": [
      {
        "key": "body"
      }
    ],
    "name": "UpdateQuery",
    "pageId": "Product View",
    "runBehaviour": "MANUAL",
    "userSetOnLoad": false
  }
}