{
  "animateLoading": true,
  "borderRadius": "{{appsmith.theme.borderRadius.appBorderRadius}}",
  "bottomRow": 12,
  "dynamicBindingPathList": [
    {
      "key": "truncateButtonColor"
    },
    {
      "key": "fontFamily"
    },
    {
      "key": "borderRadius"
    },
    {
      "key": "text"
    }
  ],
  "dynamicHeight": "AUTO_HEIGHT",
  "dynamicTriggerPathList": [],
  "fontFamily": "{{appsmith.theme.fontFamily.appFont}}",
  "fontSize": "1rem",
  "fontStyle": "BOLD",
  "isLoading": false,
  "isVisible": true,
  "key": "0z0jmfd539",
  "leftColumn": 0,
  "maxDynamicHeight": 9000,
  "minDynamicHeight": 4,
  "minWidth": 450,
  "mobileBottomRow": 30,
  "mobileLeftColumn": 25,
  "mobileRightColumn": 41,
  "mobileTopRow": 26,
  "needsErrorInfo": false,
  "originalBottomRow": 12,
  "originalTopRow": 5,
  "overflow": "NONE",
  "parentColumnSpace": 6.84375,
  "parentId": "0",
  "parentRowSpace": 10,
  "renderMode": "CANVAS",
  "responsiveBehavior": "fill",
  "rightColumn": 37,
  "shouldTruncate": false,
  "text": "SKU: {{Get_Individual_Product.data[0].sku}}\n\nPrice: £{{Get_Individual_Product.data[0].price}}",
  "textAlign": "LEFT",
  "textColor": "#231F20",
  "topRow": 5,
  "truncateButtonColor": "{{appsmith.theme.colors.primaryColor}}",
  "type": "TEXT_WIDGET",
  "version": 1,
  "widgetId": "rlry0btb5k",
  "widgetName": "Text1"
}